README.md
setup.py
pyquantfin/SAA.py
pyquantfin/StockDaily.py
pyquantfin/Trend.py
pyquantfin/__init__.py
pyquantfin/cta.py
pyquantfin/datasets.py
pyquantfin/general.py
pyquantfin/nav_analysis.py
pyquantfin/nav_calc.py
pyquantfin/otc.py
pyquantfin/plots.py
pyquantfin/pytsalib.py
pyquantfin/talib.py
pyquantfin/utils.py
pyquantfin.egg-info/PKG-INFO
pyquantfin.egg-info/SOURCES.txt
pyquantfin.egg-info/dependency_links.txt
pyquantfin.egg-info/top_level.txt
pyquantfin/data/assets.csv
pyquantfin/data/hs300.csv
pyquantfin/data/hs300_5min.h5
pyquantfin/data/sp500.xlsx
pyquantfin/data/zz500_5min.h5