Metadata-Version: 2.1
Name: pyquantfin
Version: 0.0.4
Summary: package for quant finance lecture
Home-page: https://pypi.org/manage/projects/
Author: mortalm
Author-email: mortalm@sina.com
License: UNKNOWN
Platform: UNKNOWN
